<soap:Envelope xmlns:soap="http://www.w3.org/2003/05/soap-envelope" xmlns:ns="http://at.dsh.cms.gov/exchange/1.0" xmlns:ns1="http://niem.gov/niem/structures/2.0" xmlns:ns2="http://at.dsh.cms.gov/extension/1.0" xmlns:ns3="http://niem.gov/niem/niem-core/2.0" xmlns:hix="http://hix.cms.gov/0.1/hix-core" xmlns:hix1="http://hix.cms.gov/0.1/hix-ee" xmlns:ns4="http://niem.gov/niem/domains/screening/2.1" xmlns:hix2="http://hix.cms.gov/0.1/hix-pm">
   <soap:Header/>
   <soap:Body>
<exch:AccountTransferRequest ext:atVersionText="2.4" xmlns:exch="http://at.dsh.cms.gov/exchange/1.0" xmlns:s="http://niem.gov/niem/structures/2.0" xmlns:ext="http://at.dsh.cms.gov/extension/1.0" xmlns:hix-core="http://hix.cms.gov/0.1/hix-core" xmlns:hix-ee="http://hix.cms.gov/0.1/hix-ee" xmlns:nc="http://niem.gov/niem/niem-core/2.0" xmlns:hix-pm="http://hix.cms.gov/0.1/hix-pm" xmlns:scr="http://niem.gov/niem/domains/screening/2.1" xmlns:xsi="http://www.w3.org/2001/XMLSchema-instance">
  <ext:TransferHeader>
    <ext:TransferActivity>
      <nc:ActivityIdentification>
        <nc:IdentificationID>FFM63662504036930611</nc:IdentificationID>
      </nc:ActivityIdentification>
      <nc:ActivityDate>
        <nc:DateTime>2024-07-25T13:34:36.501-05:00</nc:DateTime>
      </nc:ActivityDate>
      <ext:TransferActivityReferralQuantity>2</ext:TransferActivityReferralQuantity>
      <ext:RecipientTransferActivityCode>MedicaidCHIP</ext:RecipientTransferActivityCode>
      <ext:RecipientTransferActivityStateCode>LA</ext:RecipientTransferActivityStateCode>
    </ext:TransferActivity>
  </ext:TransferHeader>
  <hix-core:Sender s:id="Sender">
    <hix-core:InformationExchangeSystemCategoryCode>Exchange</hix-core:InformationExchangeSystemCategoryCode>
    <hix-core:InformationExchangeSystemStateCode>LA</hix-core:InformationExchangeSystemStateCode>
  </hix-core:Sender>
  <hix-core:Receiver s:id="medicaidReceiver">
    <hix-core:InformationExchangeSystemCategoryCode>MedicaidAgency</hix-core:InformationExchangeSystemCategoryCode>
    <hix-core:InformationExchangeSystemStateCode>LA</hix-core:InformationExchangeSystemStateCode>
  </hix-core:Receiver>
  <hix-ee:InsuranceApplication>
    <hix-core:ApplicationCreation>
      <nc:ActivityDate>
        <nc:DateTime>2024-07-25T13:10:39.345-05:00</nc:DateTime>
      </nc:ActivityDate>
    </hix-core:ApplicationCreation>
    <hix-core:ApplicationSubmission>
      <nc:ActivityDate>
        <nc:DateTime>2024-07-25T13:34:32.185-05:00</nc:DateTime>
      </nc:ActivityDate>
    </hix-core:ApplicationSubmission>
    <hix-core:ApplicationUpdate>
      <nc:ActivityDate>
        <nc:DateTime>2024-07-25T13:34:33.415-05:00</nc:DateTime>
      </nc:ActivityDate>
    </hix-core:ApplicationUpdate>
    <hix-core:ApplicationIdentification>
      <nc:IdentificationID>4846615710</nc:IdentificationID>
      <nc:IdentificationCategoryText>Exchange</nc:IdentificationCategoryText>
    </hix-core:ApplicationIdentification>
    <hix-ee:InsuranceApplicant>
      <hix-core:RoleOfPersonReference s:ref="pe606552526913774413"/>
      <hix-ee:InsuranceApplicantBlindnessOrDisabilityIndicator>false</hix-ee:InsuranceApplicantBlindnessOrDisabilityIndicator>
      <hix-ee:InsuranceApplicantFixedAddressIndicator>true</hix-ee:InsuranceApplicantFixedAddressIndicator>
      <hix-ee:InsuranceApplicantIncarceration>
        <hix-core:IncarcerationIndicator>false</hix-core:IncarcerationIndicator>
      </hix-ee:InsuranceApplicantIncarceration>
      <hix-ee:InsuranceApplicantLongTermCareIndicator>false</hix-ee:InsuranceApplicantLongTermCareIndicator>
      <hix-ee:InsuranceApplicantNonESICoverageIndicator>false</hix-ee:InsuranceApplicantNonESICoverageIndicator>
      <hix-ee:InsuranceApplicantParentCaretakerIndicator>false</hix-ee:InsuranceApplicantParentCaretakerIndicator>
      <hix-ee:InsuranceApplicantRecentMedicalBillsIndicator>false</hix-ee:InsuranceApplicantRecentMedicalBillsIndicator>
      <hix-ee:EmergencyMedicaidEligibility s:id="e2488594365044915262">
        <hix-ee:MedicaidHouseholdReference s:ref="mh2488215749215813585"/>
        <hix-ee:EmergencyMedicaidIncomeEligibilityBasis>
          <hix-core:StatusIndicator>true</hix-core:StatusIndicator>
          <hix-ee:EligibilityBasisStatusCode>Complete</hix-ee:EligibilityBasisStatusCode>
          <hix-ee:EligibilityBasisDetermination>
            <nc:ActivityDate>
              <nc:DateTime>2024-07-25T13:34:32.185-05:00</nc:DateTime>
            </nc:ActivityDate>
          </hix-ee:EligibilityBasisDetermination>
        </hix-ee:EmergencyMedicaidIncomeEligibilityBasis>
      </hix-ee:EmergencyMedicaidEligibility>
      <hix-ee:MedicaidMAGIEligibility s:id="e2488594365044915261">
        <hix-ee:EligibilityDateRange>
          <nc:StartDate>
            <nc:Date>2024-07-25</nc:Date>
          </nc:StartDate>
        </hix-ee:EligibilityDateRange>
        <hix-ee:EligibilityDetermination>
          <nc:ActivityDate>
            <nc:DateTime>2024-07-25T13:10:39.345-05:00</nc:DateTime>
          </nc:ActivityDate>
        </hix-ee:EligibilityDetermination>
        <hix-ee:EligibilityReasonText>999</hix-ee:EligibilityReasonText>
        <hix-ee:EligibilityIndicator>true</hix-ee:EligibilityIndicator>
        <hix-ee:EligibilityEstablishingSystem>
          <hix-core:InformationExchangeSystemCategoryCode>Exchange</hix-core:InformationExchangeSystemCategoryCode>
        </hix-ee:EligibilityEstablishingSystem>
        <hix-ee:MedicaidHouseholdReference s:ref="mh2488215749215813585"/>
        <hix-ee:MedicaidMAGIIncomeEligibilityBasis>
          <hix-core:StatusIndicator>true</hix-core:StatusIndicator>
          <hix-ee:EligibilityBasisStatusCode>Complete</hix-ee:EligibilityBasisStatusCode>
          <hix-ee:EligibilityBasisDetermination>
            <nc:ActivityDate>
              <nc:DateTime>2024-07-25T13:34:32.185-05:00</nc:DateTime>
            </nc:ActivityDate>
          </hix-ee:EligibilityBasisDetermination>
          <hix-ee:IncomeCompatibility>
            <hix-ee:IncomeCompatibilityVerificationIndicator>true</hix-ee:IncomeCompatibilityVerificationIndicator>
            <hix-ee:IncomeCompatibilityInconsistencyReasonText>564</hix-ee:IncomeCompatibilityInconsistencyReasonText>
            <hix-ee:IncomeCompatibilityDetermination>
              <nc:ActivityDate>
                <nc:DateTime>2024-07-25T13:10:39.345-05:00</nc:DateTime>
              </nc:ActivityDate>
            </hix-ee:IncomeCompatibilityDetermination>
            <hix-ee:IncomeCompatibilityVerificationMethod>4</hix-ee:IncomeCompatibilityVerificationMethod>
          </hix-ee:IncomeCompatibility>
          <hix-ee:IncomeEligibilityBasisStateThresholdFPLPercent>133</hix-ee:IncomeEligibilityBasisStateThresholdFPLPercent>
          <hix-ee:IncomeEligibilityBasisRPCRulesAppliedIndicator>false</hix-ee:IncomeEligibilityBasisRPCRulesAppliedIndicator>
        </hix-ee:MedicaidMAGIIncomeEligibilityBasis>
        <hix-ee:MedicaidMAGIResidencyEligibilityBasis>
          <hix-core:StatusIndicator>true</hix-core:StatusIndicator>
          <hix-ee:EligibilityBasisStatusCode>Complete</hix-ee:EligibilityBasisStatusCode>
          <hix-ee:EligibilityBasisDetermination>
            <nc:ActivityDate>
              <nc:DateTime>2024-07-25T13:10:39.345-05:00</nc:DateTime>
            </nc:ActivityDate>
          </hix-ee:EligibilityBasisDetermination>
          <hix-ee:MedicaidResidencyEligibilityBasisStudentRuleIndicator>false</hix-ee:MedicaidResidencyEligibilityBasisStudentRuleIndicator>
          <hix-ee:MedicaidResidencyEligibilityBasisCorrectStateIndicator>true</hix-ee:MedicaidResidencyEligibilityBasisCorrectStateIndicator>
        </hix-ee:MedicaidMAGIResidencyEligibilityBasis>
        <hix-ee:MedicaidMAGIParentCaretakerCategoryEligibilityBasis>
          <hix-core:StatusIndicator>false</hix-core:StatusIndicator>
          <hix-ee:EligibilityBasisStatusCode>Complete</hix-ee:EligibilityBasisStatusCode>
          <hix-ee:EligibilityBasisIneligibilityReasonText>146</hix-ee:EligibilityBasisIneligibilityReasonText>
          <hix-ee:EligibilityBasisDetermination>
            <nc:ActivityDate>
              <nc:DateTime>2024-07-25T13:10:39.345-05:00</nc:DateTime>
            </nc:ActivityDate>
          </hix-ee:EligibilityBasisDetermination>
        </hix-ee:MedicaidMAGIParentCaretakerCategoryEligibilityBasis>
        <hix-ee:MedicaidMAGIChildCategoryEligibilityBasis>
          <hix-core:StatusIndicator>false</hix-core:StatusIndicator>
          <hix-ee:EligibilityBasisStatusCode>Complete</hix-ee:EligibilityBasisStatusCode>
          <hix-ee:EligibilityBasisIneligibilityReasonText>115</hix-ee:EligibilityBasisIneligibilityReasonText>
          <hix-ee:EligibilityBasisDetermination>
            <nc:ActivityDate>
              <nc:DateTime>2024-07-25T13:10:39.345-05:00</nc:DateTime>
            </nc:ActivityDate>
          </hix-ee:EligibilityBasisDetermination>
        </hix-ee:MedicaidMAGIChildCategoryEligibilityBasis>
        <hix-ee:MedicaidMAGIAdultGroupCategoryEligibilityBasis>
          <hix-core:StatusIndicator>true</hix-core:StatusIndicator>
          <hix-ee:EligibilityBasisStatusCode>Complete</hix-ee:EligibilityBasisStatusCode>
          <hix-ee:EligibilityBasisDetermination>
            <nc:ActivityDate>
              <nc:DateTime>2024-07-25T13:10:39.345-05:00</nc:DateTime>
            </nc:ActivityDate>
          </hix-ee:EligibilityBasisDetermination>
        </hix-ee:MedicaidMAGIAdultGroupCategoryEligibilityBasis>
        <hix-ee:MedicaidMAGIAdultGroupXXCategoryEligibilityBasis>
          <hix-ee:EligibilityBasisStatusCode>NotApplicable</hix-ee:EligibilityBasisStatusCode>
          <hix-ee:EligibilityBasisIneligibilityReasonText>586</hix-ee:EligibilityBasisIneligibilityReasonText>
          <hix-ee:EligibilityBasisDetermination>
            <nc:ActivityDate>
              <nc:DateTime>2024-07-25T13:10:39.345-05:00</nc:DateTime>
            </nc:ActivityDate>
          </hix-ee:EligibilityBasisDetermination>
        </hix-ee:MedicaidMAGIAdultGroupXXCategoryEligibilityBasis>
        <hix-ee:MedicaidMAGIOptionalTargetedLowIncomeChildEligibilityBasis>
          <hix-core:StatusIndicator>false</hix-core:StatusIndicator>
          <hix-ee:EligibilityBasisStatusCode>Complete</hix-ee:EligibilityBasisStatusCode>
          <hix-ee:EligibilityBasisIneligibilityReasonText>127</hix-ee:EligibilityBasisIneligibilityReasonText>
          <hix-ee:EligibilityBasisDetermination>
            <nc:ActivityDate>
              <nc:DateTime>2024-07-25T13:10:39.345-05:00</nc:DateTime>
            </nc:ActivityDate>
          </hix-ee:EligibilityBasisDetermination>
        </hix-ee:MedicaidMAGIOptionalTargetedLowIncomeChildEligibilityBasis>
        <hix-ee:MedicaidMAGICitizenOrImmigrantEligibilityBasis>
          <hix-core:StatusIndicator>true</hix-core:StatusIndicator>
          <hix-ee:EligibilityBasisStatusCode>Complete</hix-ee:EligibilityBasisStatusCode>
          <hix-ee:EligibilityBasisDetermination>
            <nc:ActivityDate>
              <nc:DateTime>2024-07-25T13:10:39.345-05:00</nc:DateTime>
            </nc:ActivityDate>
          </hix-ee:EligibilityBasisDetermination>
        </hix-ee:MedicaidMAGICitizenOrImmigrantEligibilityBasis>
        <hix-ee:MedicaidMAGI-CHIPRA214EligibilityBasis>
          <hix-ee:EligibilityBasisStatusCode>NotApplicable</hix-ee:EligibilityBasisStatusCode>
          <hix-ee:EligibilityBasisIneligibilityReasonText>612</hix-ee:EligibilityBasisIneligibilityReasonText>
          <hix-ee:EligibilityBasisDetermination>
            <nc:ActivityDate>
              <nc:DateTime>2024-07-25T13:10:39.345-05:00</nc:DateTime>
            </nc:ActivityDate>
          </hix-ee:EligibilityBasisDetermination>
        </hix-ee:MedicaidMAGI-CHIPRA214EligibilityBasis>
        <hix-ee:MedicaidMAGISevenYearLimitEligibilityBasis>
          <hix-ee:EligibilityBasisStatusCode>NotApplicable</hix-ee:EligibilityBasisStatusCode>
          <hix-ee:EligibilityBasisIneligibilityReasonText>569</hix-ee:EligibilityBasisIneligibilityReasonText>
          <hix-ee:EligibilityBasisDetermination>
            <nc:ActivityDate>
              <nc:DateTime>2024-07-25T13:10:39.345-05:00</nc:DateTime>
            </nc:ActivityDate>
          </hix-ee:EligibilityBasisDetermination>
        </hix-ee:MedicaidMAGISevenYearLimitEligibilityBasis>
        <hix-ee:MedicaidMAGIFormerFosterCareCategoryEligibilityBasis>
          <hix-core:StatusIndicator>false</hix-core:StatusIndicator>
          <hix-ee:EligibilityBasisStatusCode>Complete</hix-ee:EligibilityBasisStatusCode>
          <hix-ee:EligibilityBasisIneligibilityReasonText>647</hix-ee:EligibilityBasisIneligibilityReasonText>
          <hix-ee:EligibilityBasisDetermination>
            <nc:ActivityDate>
              <nc:DateTime>2024-07-25T13:10:39.345-05:00</nc:DateTime>
            </nc:ActivityDate>
          </hix-ee:EligibilityBasisDetermination>
        </hix-ee:MedicaidMAGIFormerFosterCareCategoryEligibilityBasis>
        <hix-ee:MedicaidMAGIDependentChildCoverageEligibilityBasis>
          <hix-ee:EligibilityBasisStatusCode>NotApplicable</hix-ee:EligibilityBasisStatusCode>
          <hix-ee:EligibilityBasisIneligibilityReasonText>555</hix-ee:EligibilityBasisIneligibilityReasonText>
          <hix-ee:EligibilityBasisDetermination>
            <nc:ActivityDate>
              <nc:DateTime>2024-07-25T13:10:39.345-05:00</nc:DateTime>
            </nc:ActivityDate>
          </hix-ee:EligibilityBasisDetermination>
        </hix-ee:MedicaidMAGIDependentChildCoverageEligibilityBasis>
        <hix-ee:MedicaidMAGIFiveYearBarEligibilityBasis>
          <hix-ee:EligibilityBasisStatusCode>NotApplicable</hix-ee:EligibilityBasisStatusCode>
          <hix-ee:EligibilityBasisIneligibilityReasonText>569</hix-ee:EligibilityBasisIneligibilityReasonText>
        </hix-ee:MedicaidMAGIFiveYearBarEligibilityBasis>
        <hix-ee:MedicaidMAGISSNVerificationEligibilityBasis>
          <hix-core:StatusIndicator>true</hix-core:StatusIndicator>
          <hix-ee:EligibilityBasisStatusCode>Complete</hix-ee:EligibilityBasisStatusCode>
          <hix-ee:EligibilityBasisDetermination>
            <nc:ActivityDate>
              <nc:DateTime>2024-07-25T13:16:24.537-05:00</nc:DateTime>
            </nc:ActivityDate>
          </hix-ee:EligibilityBasisDetermination>
        </hix-ee:MedicaidMAGISSNVerificationEligibilityBasis>
      </hix-ee:MedicaidMAGIEligibility>
      <hix-ee:MedicaidNonMAGIEligibility s:id="e2488594365044915264">
        <hix-ee:EligibilityDetermination>
          <nc:ActivityDate>
            <nc:DateTime>2024-07-25T13:10:39.345-05:00</nc:DateTime>
          </nc:ActivityDate>
        </hix-ee:EligibilityDetermination>
        <hix-ee:EligibilityReasonText>108</hix-ee:EligibilityReasonText>
        <hix-ee:EligibilityIndicator>false</hix-ee:EligibilityIndicator>
        <hix-ee:EligibilityEstablishingSystem>
          <hix-core:InformationExchangeSystemCategoryCode>Exchange</hix-core:InformationExchangeSystemCategoryCode>
        </hix-ee:EligibilityEstablishingSystem>
        <hix-ee:MedicaidHouseholdReference s:ref="mh2488215749215813585"/>
        <hix-ee:MedicaidNonMAGIBlindnessOrDisabilityEligibilityBasis>
          <hix-core:StatusIndicator>false</hix-core:StatusIndicator>
          <hix-ee:EligibilityBasisStatusCode>Complete</hix-ee:EligibilityBasisStatusCode>
        </hix-ee:MedicaidNonMAGIBlindnessOrDisabilityEligibilityBasis>
      </hix-ee:MedicaidNonMAGIEligibility>
      <hix-ee:APTCEligibility s:id="e2488594365044915265">
        <hix-ee:EligibilityDetermination>
          <nc:ActivityDate>
            <nc:DateTime>2024-07-25T13:10:39.345-05:00</nc:DateTime>
          </nc:ActivityDate>
        </hix-ee:EligibilityDetermination>
        <hix-ee:EligibilityReasonText>600</hix-ee:EligibilityReasonText>
        <hix-ee:EligibilityIndicator>false</hix-ee:EligibilityIndicator>
      </hix-ee:APTCEligibility>
      <hix-ee:CHIPEligibility s:id="e2488594365044915263">
        <hix-ee:EligibilityDateRange>
          <nc:StartDate>
            <nc:Date>2024-07-25</nc:Date>
          </nc:StartDate>
        </hix-ee:EligibilityDateRange>
        <hix-ee:EligibilityDetermination>
          <nc:ActivityDate>
            <nc:DateTime>2024-07-25T13:34:32.185-05:00</nc:DateTime>
          </nc:ActivityDate>
        </hix-ee:EligibilityDetermination>
        <hix-ee:EligibilityReasonText>107</hix-ee:EligibilityReasonText>
        <hix-ee:EligibilityIndicator>false</hix-ee:EligibilityIndicator>
        <hix-ee:EligibilityEstablishingSystem>
          <hix-core:InformationExchangeSystemCategoryCode>Exchange</hix-core:InformationExchangeSystemCategoryCode>
        </hix-ee:EligibilityEstablishingSystem>
        <hix-ee:CHIPIncomeEligibilityBasis>
          <hix-core:StatusIndicator>false</hix-core:StatusIndicator>
          <hix-ee:EligibilityBasisStatusCode>Complete</hix-ee:EligibilityBasisStatusCode>
          <hix-ee:EligibilityBasisIneligibilityReasonText>564</hix-ee:EligibilityBasisIneligibilityReasonText>
          <hix-ee:EligibilityBasisDetermination>
            <nc:ActivityDate>
              <nc:DateTime>2024-07-25T13:30:39.876-05:00</nc:DateTime>
            </nc:ActivityDate>
          </hix-ee:EligibilityBasisDetermination>
          <hix-ee:IncomeEligibilityBasisStateThresholdFPLPercent>0</hix-ee:IncomeEligibilityBasisStateThresholdFPLPercent>
        </hix-ee:CHIPIncomeEligibilityBasis>
        <hix-ee:CHIPMedicaidResidencyEligibilityBasis>
          <hix-core:StatusIndicator>true</hix-core:StatusIndicator>
          <hix-ee:EligibilityBasisStatusCode>Complete</hix-ee:EligibilityBasisStatusCode>
          <hix-ee:EligibilityBasisDetermination>
            <nc:ActivityDate>
              <nc:DateTime>2024-07-25T13:10:39.345-05:00</nc:DateTime>
            </nc:ActivityDate>
          </hix-ee:EligibilityBasisDetermination>
          <hix-ee:MedicaidResidencyEligibilityBasisCorrectStateIndicator>true</hix-ee:MedicaidResidencyEligibilityBasisCorrectStateIndicator>
        </hix-ee:CHIPMedicaidResidencyEligibilityBasis>
        <hix-ee:CHIPTargetedLowIncomeChildEligibilityBasis>
          <hix-core:StatusIndicator>false</hix-core:StatusIndicator>
          <hix-ee:EligibilityBasisStatusCode>Complete</hix-ee:EligibilityBasisStatusCode>
          <hix-ee:EligibilityBasisIneligibilityReasonText>127</hix-ee:EligibilityBasisIneligibilityReasonText>
          <hix-ee:EligibilityBasisDetermination>
            <nc:ActivityDate>
              <nc:DateTime>2024-07-25T13:10:39.345-05:00</nc:DateTime>
            </nc:ActivityDate>
          </hix-ee:EligibilityBasisDetermination>
        </hix-ee:CHIPTargetedLowIncomeChildEligibilityBasis>
        <hix-ee:CHIPUnbornChildCategoryEligibilityBasis>
          <hix-ee:EligibilityBasisStatusCode>NotApplicable</hix-ee:EligibilityBasisStatusCode>
          <hix-ee:EligibilityBasisIneligibilityReasonText>555</hix-ee:EligibilityBasisIneligibilityReasonText>
          <hix-ee:EligibilityBasisDetermination>
            <nc:ActivityDate>
              <nc:DateTime>2024-07-25T13:34:32.185-05:00</nc:DateTime>
            </nc:ActivityDate>
          </hix-ee:EligibilityBasisDetermination>
        </hix-ee:CHIPUnbornChildCategoryEligibilityBasis>
        <hix-ee:CHIPStateHealthBenefitsEligibilityBasis>
          <hix-ee:EligibilityBasisStatusCode>NotApplicable</hix-ee:EligibilityBasisStatusCode>
          <hix-ee:EligibilityBasisDetermination>
            <nc:ActivityDate>
              <nc:DateTime>2024-07-25T13:10:39.345-05:00</nc:DateTime>
            </nc:ActivityDate>
          </hix-ee:EligibilityBasisDetermination>
        </hix-ee:CHIPStateHealthBenefitsEligibilityBasis>
        <hix-ee:CHIPWaitingPeriodEligibilityBasis>
          <hix-ee:EligibilityBasisStatusCode>NotApplicable</hix-ee:EligibilityBasisStatusCode>
          <hix-ee:EligibilityBasisDetermination>
            <nc:ActivityDate>
              <nc:DateTime>2024-07-25T13:10:39.345-05:00</nc:DateTime>
            </nc:ActivityDate>
          </hix-ee:EligibilityBasisDetermination>
        </hix-ee:CHIPWaitingPeriodEligibilityBasis>
        <hix-ee:CHIPTraffickingVictimCategoryEligibilityBasis>
          <hix-ee:EligibilityBasisStatusCode>NotApplicable</hix-ee:EligibilityBasisStatusCode>
          <hix-ee:EligibilityBasisIneligibilityReasonText>569</hix-ee:EligibilityBasisIneligibilityReasonText>
          <hix-ee:EligibilityBasisDetermination>
            <nc:ActivityDate>
              <nc:DateTime>2024-07-25T13:10:39.345-05:00</nc:DateTime>
            </nc:ActivityDate>
          </hix-ee:EligibilityBasisDetermination>
        </hix-ee:CHIPTraffickingVictimCategoryEligibilityBasis>
        <hix-ee:CHIPTitleIIWorkQuartersMetEligibilityBasis>
          <hix-ee:EligibilityBasisStatusCode>NotApplicable</hix-ee:EligibilityBasisStatusCode>
          <hix-ee:EligibilityBasisIneligibilityReasonText>632</hix-ee:EligibilityBasisIneligibilityReasonText>
          <hix-ee:EligibilityBasisDetermination>
            <nc:ActivityDate>
              <nc:DateTime>2024-07-25T13:10:39.345-05:00</nc:DateTime>
            </nc:ActivityDate>
          </hix-ee:EligibilityBasisDetermination>
        </hix-ee:CHIPTitleIIWorkQuartersMetEligibilityBasis>
        <hix-ee:MedicaidHouseholdReference s:ref="mh2488215749215813585"/>
      </hix-ee:CHIPEligibility>
      <hix-ee:ExchangeEligibility s:id="e2488594365044915266">
        <hix-ee:EligibilityDetermination>
          <nc:ActivityDate>
            <nc:DateTime>2024-07-25T13:10:39.345-05:00</nc:DateTime>
          </nc:ActivityDate>
        </hix-ee:EligibilityDetermination>
        <hix-ee:EligibilityEstablishingSystem>
          <hix-core:InformationExchangeSystemCategoryCode>Exchange</hix-core:InformationExchangeSystemCategoryCode>
        </hix-ee:EligibilityEstablishingSystem>
        <hix-ee:ExchangeQHPResidencyEligibilityBasis>
          <hix-core:StatusIndicator>true</hix-core:StatusIndicator>
          <hix-ee:EligibilityBasisStatusCode>Complete</hix-ee:EligibilityBasisStatusCode>
          <hix-ee:EligibilityBasisDetermination>
            <nc:ActivityDate>
              <nc:DateTime>2024-07-25T13:14:05.441-05:00</nc:DateTime>
            </nc:ActivityDate>
          </hix-ee:EligibilityBasisDetermination>
          <hix-ee:MedicaidResidencyEligibilityBasisCorrectStateIndicator>true</hix-ee:MedicaidResidencyEligibilityBasisCorrectStateIndicator>
        </hix-ee:ExchangeQHPResidencyEligibilityBasis>
        <hix-ee:ExchangeVerifiedCitizenshipOrLawfulPresenceEligibilityBasis>
          <hix-core:StatusIndicator>true</hix-core:StatusIndicator>
          <hix-ee:EligibilityBasisStatusCode>Complete</hix-ee:EligibilityBasisStatusCode>
          <hix-ee:EligibilityBasisDetermination>
            <nc:ActivityDate>
              <nc:DateTime>2024-07-25T13:34:31.417-05:00</nc:DateTime>
            </nc:ActivityDate>
          </hix-ee:EligibilityBasisDetermination>
        </hix-ee:ExchangeVerifiedCitizenshipOrLawfulPresenceEligibilityBasis>
      </hix-ee:ExchangeEligibility>
      <hix-ee:ReferralActivity>
        <nc:ActivityIdentification>
          <nc:IdentificationID>FFM63662504036930611</nc:IdentificationID>
        </nc:ActivityIdentification>
        <nc:ActivityDate>
          <nc:DateTime>2024-07-25T13:34:36.501-05:00</nc:DateTime>
        </nc:ActivityDate>
        <hix-ee:ReferralActivitySenderReference s:ref="Sender"/>
        <hix-ee:ReferralActivityReceiverReference s:ref="medicaidReceiver"/>
        <hix-ee:ReferralActivityStatus>
          <hix-ee:ReferralActivityStatusCode>Initiated</hix-ee:ReferralActivityStatusCode>
          <hix-ee:ReferralActivityOverallVerificationStatusCode>Y</hix-ee:ReferralActivityOverallVerificationStatusCode>
        </hix-ee:ReferralActivityStatus>
        <hix-ee:ReferralActivityReasonCode>GapFilling</hix-ee:ReferralActivityReasonCode>
        <hix-ee:ReferralActivityEligibilityReasonReference s:ref="e2488594365044915261"/>
      </hix-ee:ReferralActivity>
    </hix-ee:InsuranceApplicant>
    <hix-ee:InsuranceApplicant>
      <hix-core:RoleOfPersonReference s:ref="pe2488551408249964720"/>
      <hix-ee:InsuranceApplicantBlindnessOrDisabilityIndicator>false</hix-ee:InsuranceApplicantBlindnessOrDisabilityIndicator>
      <hix-ee:InsuranceApplicantFixedAddressIndicator>true</hix-ee:InsuranceApplicantFixedAddressIndicator>
      <hix-ee:InsuranceApplicantIncarceration>
        <hix-core:IncarcerationIndicator>false</hix-core:IncarcerationIndicator>
      </hix-ee:InsuranceApplicantIncarceration>
      <hix-ee:InsuranceApplicantLongTermCareIndicator>false</hix-ee:InsuranceApplicantLongTermCareIndicator>
      <hix-ee:InsuranceApplicantNonESICoverageIndicator>false</hix-ee:InsuranceApplicantNonESICoverageIndicator>
      <hix-ee:InsuranceApplicantParentCaretakerIndicator>false</hix-ee:InsuranceApplicantParentCaretakerIndicator>
      <hix-ee:InsuranceApplicantRecentMedicalBillsIndicator>false</hix-ee:InsuranceApplicantRecentMedicalBillsIndicator>
      <hix-ee:EmergencyMedicaidEligibility s:id="e2488594365044915268">
        <hix-ee:MedicaidHouseholdReference s:ref="mh2488215749215813586"/>
        <hix-ee:EmergencyMedicaidIncomeEligibilityBasis>
          <hix-core:StatusIndicator>true</hix-core:StatusIndicator>
          <hix-ee:EligibilityBasisStatusCode>Complete</hix-ee:EligibilityBasisStatusCode>
          <hix-ee:EligibilityBasisDetermination>
            <nc:ActivityDate>
              <nc:DateTime>2024-07-25T13:34:32.185-05:00</nc:DateTime>
            </nc:ActivityDate>
          </hix-ee:EligibilityBasisDetermination>
        </hix-ee:EmergencyMedicaidIncomeEligibilityBasis>
      </hix-ee:EmergencyMedicaidEligibility>
      <hix-ee:MedicaidMAGIEligibility s:id="e2488594365044915267">
        <hix-ee:EligibilityDateRange>
          <nc:StartDate>
            <nc:Date>2024-07-25</nc:Date>
          </nc:StartDate>
        </hix-ee:EligibilityDateRange>
        <hix-ee:EligibilityDetermination>
          <nc:ActivityDate>
            <nc:DateTime>2024-07-25T13:10:39.345-05:00</nc:DateTime>
          </nc:ActivityDate>
        </hix-ee:EligibilityDetermination>
        <hix-ee:EligibilityReasonText>999</hix-ee:EligibilityReasonText>
        <hix-ee:EligibilityIndicator>true</hix-ee:EligibilityIndicator>
        <hix-ee:EligibilityEstablishingSystem>
          <hix-core:InformationExchangeSystemCategoryCode>Exchange</hix-core:InformationExchangeSystemCategoryCode>
        </hix-ee:EligibilityEstablishingSystem>
        <hix-ee:MedicaidHouseholdReference s:ref="mh2488215749215813586"/>
        <hix-ee:MedicaidMAGIIncomeEligibilityBasis>
          <hix-core:StatusIndicator>true</hix-core:StatusIndicator>
          <hix-ee:EligibilityBasisStatusCode>Complete</hix-ee:EligibilityBasisStatusCode>
          <hix-ee:EligibilityBasisDetermination>
            <nc:ActivityDate>
              <nc:DateTime>2024-07-25T13:34:32.185-05:00</nc:DateTime>
            </nc:ActivityDate>
          </hix-ee:EligibilityBasisDetermination>
          <hix-ee:IncomeCompatibility>
            <hix-ee:IncomeCompatibilityVerificationIndicator>true</hix-ee:IncomeCompatibilityVerificationIndicator>
            <hix-ee:IncomeCompatibilityInconsistencyReasonText>564</hix-ee:IncomeCompatibilityInconsistencyReasonText>
            <hix-ee:IncomeCompatibilityDetermination>
              <nc:ActivityDate>
                <nc:DateTime>2024-07-25T13:10:39.345-05:00</nc:DateTime>
              </nc:ActivityDate>
            </hix-ee:IncomeCompatibilityDetermination>
            <hix-ee:IncomeCompatibilityVerificationMethod>4</hix-ee:IncomeCompatibilityVerificationMethod>
          </hix-ee:IncomeCompatibility>
          <hix-ee:IncomeEligibilityBasisStateThresholdFPLPercent>133</hix-ee:IncomeEligibilityBasisStateThresholdFPLPercent>
          <hix-ee:IncomeEligibilityBasisRPCRulesAppliedIndicator>false</hix-ee:IncomeEligibilityBasisRPCRulesAppliedIndicator>
        </hix-ee:MedicaidMAGIIncomeEligibilityBasis>
        <hix-ee:MedicaidMAGIResidencyEligibilityBasis>
          <hix-core:StatusIndicator>true</hix-core:StatusIndicator>
          <hix-ee:EligibilityBasisStatusCode>Complete</hix-ee:EligibilityBasisStatusCode>
          <hix-ee:EligibilityBasisDetermination>
            <nc:ActivityDate>
              <nc:DateTime>2024-07-25T13:10:39.345-05:00</nc:DateTime>
            </nc:ActivityDate>
          </hix-ee:EligibilityBasisDetermination>
          <hix-ee:MedicaidResidencyEligibilityBasisStudentRuleIndicator>false</hix-ee:MedicaidResidencyEligibilityBasisStudentRuleIndicator>
          <hix-ee:MedicaidResidencyEligibilityBasisCorrectStateIndicator>true</hix-ee:MedicaidResidencyEligibilityBasisCorrectStateIndicator>
        </hix-ee:MedicaidMAGIResidencyEligibilityBasis>
        <hix-ee:MedicaidMAGIParentCaretakerCategoryEligibilityBasis>
          <hix-core:StatusIndicator>false</hix-core:StatusIndicator>
          <hix-ee:EligibilityBasisStatusCode>Complete</hix-ee:EligibilityBasisStatusCode>
          <hix-ee:EligibilityBasisIneligibilityReasonText>146</hix-ee:EligibilityBasisIneligibilityReasonText>
          <hix-ee:EligibilityBasisDetermination>
            <nc:ActivityDate>
              <nc:DateTime>2024-07-25T13:10:39.345-05:00</nc:DateTime>
            </nc:ActivityDate>
          </hix-ee:EligibilityBasisDetermination>
        </hix-ee:MedicaidMAGIParentCaretakerCategoryEligibilityBasis>
        <hix-ee:MedicaidMAGIChildCategoryEligibilityBasis>
          <hix-core:StatusIndicator>false</hix-core:StatusIndicator>
          <hix-ee:EligibilityBasisStatusCode>Complete</hix-ee:EligibilityBasisStatusCode>
          <hix-ee:EligibilityBasisIneligibilityReasonText>115</hix-ee:EligibilityBasisIneligibilityReasonText>
          <hix-ee:EligibilityBasisDetermination>
            <nc:ActivityDate>
              <nc:DateTime>2024-07-25T13:10:39.345-05:00</nc:DateTime>
            </nc:ActivityDate>
          </hix-ee:EligibilityBasisDetermination>
        </hix-ee:MedicaidMAGIChildCategoryEligibilityBasis>
        <hix-ee:MedicaidMAGIAdultGroupCategoryEligibilityBasis>
          <hix-core:StatusIndicator>true</hix-core:StatusIndicator>
          <hix-ee:EligibilityBasisStatusCode>Complete</hix-ee:EligibilityBasisStatusCode>
          <hix-ee:EligibilityBasisDetermination>
            <nc:ActivityDate>
              <nc:DateTime>2024-07-25T13:10:39.345-05:00</nc:DateTime>
            </nc:ActivityDate>
          </hix-ee:EligibilityBasisDetermination>
       </hix-ee:MedicaidMAGIAdultGroupCategoryEligibilityBasis>
        <hix-ee:MedicaidMAGIAdultGroupXXCategoryEligibilityBasis>
          <hix-ee:EligibilityBasisStatusCode>NotApplicable</hix-ee:EligibilityBasisStatusCode>
          <hix-ee:EligibilityBasisIneligibilityReasonText>586</hix-ee:EligibilityBasisIneligibilityReasonText>
          <hix-ee:EligibilityBasisDetermination>
            <nc:ActivityDate>
              <nc:DateTime>2024-07-25T13:10:39.345-05:00</nc:DateTime>
            </nc:ActivityDate>
          </hix-ee:EligibilityBasisDetermination>
        </hix-ee:MedicaidMAGIAdultGroupXXCategoryEligibilityBasis>
        <hix-ee:MedicaidMAGIOptionalTargetedLowIncomeChildEligibilityBasis>
          <hix-core:StatusIndicator>false</hix-core:StatusIndicator>
          <hix-ee:EligibilityBasisStatusCode>Complete</hix-ee:EligibilityBasisStatusCode>
          <hix-ee:EligibilityBasisIneligibilityReasonText>127</hix-ee:EligibilityBasisIneligibilityReasonText>
          <hix-ee:EligibilityBasisDetermination>
            <nc:ActivityDate>
              <nc:DateTime>2024-07-25T13:10:39.345-05:00</nc:DateTime>
            </nc:ActivityDate>
          </hix-ee:EligibilityBasisDetermination>
        </hix-ee:MedicaidMAGIOptionalTargetedLowIncomeChildEligibilityBasis>
        <hix-ee:MedicaidMAGICitizenOrImmigrantEligibilityBasis>
          <hix-core:StatusIndicator>true</hix-core:StatusIndicator>
          <hix-ee:EligibilityBasisStatusCode>Complete</hix-ee:EligibilityBasisStatusCode>
          <hix-ee:EligibilityBasisDetermination>
            <nc:ActivityDate>
              <nc:DateTime>2024-07-25T13:10:39.345-05:00</nc:DateTime>
            </nc:ActivityDate>
          </hix-ee:EligibilityBasisDetermination>
        </hix-ee:MedicaidMAGICitizenOrImmigrantEligibilityBasis>
        <hix-ee:MedicaidMAGI-CHIPRA214EligibilityBasis>
          <hix-ee:EligibilityBasisStatusCode>NotApplicable</hix-ee:EligibilityBasisStatusCode>
          <hix-ee:EligibilityBasisIneligibilityReasonText>612</hix-ee:EligibilityBasisIneligibilityReasonText>
          <hix-ee:EligibilityBasisDetermination>
            <nc:ActivityDate>
              <nc:DateTime>2024-07-25T13:10:39.345-05:00</nc:DateTime>
            </nc:ActivityDate>
          </hix-ee:EligibilityBasisDetermination>
        </hix-ee:MedicaidMAGI-CHIPRA214EligibilityBasis>
        <hix-ee:MedicaidMAGISevenYearLimitEligibilityBasis>
          <hix-ee:EligibilityBasisStatusCode>NotApplicable</hix-ee:EligibilityBasisStatusCode>
          <hix-ee:EligibilityBasisIneligibilityReasonText>569</hix-ee:EligibilityBasisIneligibilityReasonText>
          <hix-ee:EligibilityBasisDetermination>
            <nc:ActivityDate>
              <nc:DateTime>2024-07-25T13:10:39.345-05:00</nc:DateTime>
            </nc:ActivityDate>
          </hix-ee:EligibilityBasisDetermination>
        </hix-ee:MedicaidMAGISevenYearLimitEligibilityBasis>
        <hix-ee:MedicaidMAGIFormerFosterCareCategoryEligibilityBasis>
          <hix-core:StatusIndicator>false</hix-core:StatusIndicator>
          <hix-ee:EligibilityBasisStatusCode>Complete</hix-ee:EligibilityBasisStatusCode>
          <hix-ee:EligibilityBasisIneligibilityReasonText>647</hix-ee:EligibilityBasisIneligibilityReasonText>
          <hix-ee:EligibilityBasisDetermination>
            <nc:ActivityDate>
              <nc:DateTime>2024-07-25T13:10:39.345-05:00</nc:DateTime>
            </nc:ActivityDate>
          </hix-ee:EligibilityBasisDetermination>
        </hix-ee:MedicaidMAGIFormerFosterCareCategoryEligibilityBasis>
        <hix-ee:MedicaidMAGIDependentChildCoverageEligibilityBasis>
          <hix-ee:EligibilityBasisStatusCode>NotApplicable</hix-ee:EligibilityBasisStatusCode>
          <hix-ee:EligibilityBasisIneligibilityReasonText>555</hix-ee:EligibilityBasisIneligibilityReasonText>
          <hix-ee:EligibilityBasisDetermination>
            <nc:ActivityDate>
              <nc:DateTime>2024-07-25T13:10:39.345-05:00</nc:DateTime>
            </nc:ActivityDate>
          </hix-ee:EligibilityBasisDetermination>
        </hix-ee:MedicaidMAGIDependentChildCoverageEligibilityBasis>
        <hix-ee:MedicaidMAGIFiveYearBarEligibilityBasis>
          <hix-ee:EligibilityBasisStatusCode>NotApplicable</hix-ee:EligibilityBasisStatusCode>
          <hix-ee:EligibilityBasisIneligibilityReasonText>569</hix-ee:EligibilityBasisIneligibilityReasonText>
        </hix-ee:MedicaidMAGIFiveYearBarEligibilityBasis>
        <hix-ee:MedicaidMAGISSNVerificationEligibilityBasis>
          <hix-core:StatusIndicator>true</hix-core:StatusIndicator>
          <hix-ee:EligibilityBasisStatusCode>Complete</hix-ee:EligibilityBasisStatusCode>
          <hix-ee:EligibilityBasisDetermination>
            <nc:ActivityDate>
              <nc:DateTime>2024-07-25T13:16:24.537-05:00</nc:DateTime>
            </nc:ActivityDate>
          </hix-ee:EligibilityBasisDetermination>
        </hix-ee:MedicaidMAGISSNVerificationEligibilityBasis>
      </hix-ee:MedicaidMAGIEligibility>
      <hix-ee:MedicaidNonMAGIEligibility s:id="e2488594365044915270">
        <hix-ee:EligibilityDetermination>
          <nc:ActivityDate>
            <nc:DateTime>2024-07-25T13:10:39.345-05:00</nc:DateTime>
          </nc:ActivityDate>
        </hix-ee:EligibilityDetermination>
        <hix-ee:EligibilityReasonText>108</hix-ee:EligibilityReasonText>
        <hix-ee:EligibilityIndicator>false</hix-ee:EligibilityIndicator>
        <hix-ee:EligibilityEstablishingSystem>
          <hix-core:InformationExchangeSystemCategoryCode>Exchange</hix-core:InformationExchangeSystemCategoryCode>
        </hix-ee:EligibilityEstablishingSystem>
        <hix-ee:MedicaidHouseholdReference s:ref="mh2488215749215813586"/>
        <hix-ee:MedicaidNonMAGIBlindnessOrDisabilityEligibilityBasis>
          <hix-core:StatusIndicator>false</hix-core:StatusIndicator>
          <hix-ee:EligibilityBasisStatusCode>Complete</hix-ee:EligibilityBasisStatusCode>
        </hix-ee:MedicaidNonMAGIBlindnessOrDisabilityEligibilityBasis>
      </hix-ee:MedicaidNonMAGIEligibility>
      <hix-ee:APTCEligibility s:id="e2488594365044915271">
        <hix-ee:EligibilityDetermination>
          <nc:ActivityDate>
            <nc:DateTime>2024-07-25T13:10:39.345-05:00</nc:DateTime>
          </nc:ActivityDate>
        </hix-ee:EligibilityDetermination>
        <hix-ee:EligibilityReasonText>600</hix-ee:EligibilityReasonText>
        <hix-ee:EligibilityIndicator>false</hix-ee:EligibilityIndicator>
      </hix-ee:APTCEligibility>
      <hix-ee:CHIPEligibility s:id="e2488594365044915269">
        <hix-ee:EligibilityDateRange>
          <nc:StartDate>
            <nc:Date>2024-07-25</nc:Date>
          </nc:StartDate>
        </hix-ee:EligibilityDateRange>
        <hix-ee:EligibilityDetermination>
          <nc:ActivityDate>
            <nc:DateTime>2024-07-25T13:34:32.185-05:00</nc:DateTime>
          </nc:ActivityDate>
        </hix-ee:EligibilityDetermination>
        <hix-ee:EligibilityReasonText>107</hix-ee:EligibilityReasonText>
        <hix-ee:EligibilityIndicator>false</hix-ee:EligibilityIndicator>
        <hix-ee:EligibilityEstablishingSystem>
          <hix-core:InformationExchangeSystemCategoryCode>Exchange</hix-core:InformationExchangeSystemCategoryCode>
        </hix-ee:EligibilityEstablishingSystem>
        <hix-ee:CHIPIncomeEligibilityBasis>
          <hix-core:StatusIndicator>false</hix-core:StatusIndicator>
          <hix-ee:EligibilityBasisStatusCode>Complete</hix-ee:EligibilityBasisStatusCode>
          <hix-ee:EligibilityBasisIneligibilityReasonText>564</hix-ee:EligibilityBasisIneligibilityReasonText>
          <hix-ee:EligibilityBasisDetermination>
            <nc:ActivityDate>
              <nc:DateTime>2024-07-25T13:30:39.876-05:00</nc:DateTime>
            </nc:ActivityDate>
          </hix-ee:EligibilityBasisDetermination>
          <hix-ee:IncomeEligibilityBasisStateThresholdFPLPercent>0</hix-ee:IncomeEligibilityBasisStateThresholdFPLPercent>
        </hix-ee:CHIPIncomeEligibilityBasis>
        <hix-ee:CHIPMedicaidResidencyEligibilityBasis>
          <hix-core:StatusIndicator>true</hix-core:StatusIndicator>
          <hix-ee:EligibilityBasisStatusCode>Complete</hix-ee:EligibilityBasisStatusCode>
          <hix-ee:EligibilityBasisDetermination>
            <nc:ActivityDate>
              <nc:DateTime>2024-07-25T13:10:39.345-05:00</nc:DateTime>
            </nc:ActivityDate>
          </hix-ee:EligibilityBasisDetermination>
          <hix-ee:MedicaidResidencyEligibilityBasisCorrectStateIndicator>true</hix-ee:MedicaidResidencyEligibilityBasisCorrectStateIndicator>
        </hix-ee:CHIPMedicaidResidencyEligibilityBasis>
        <hix-ee:CHIPTargetedLowIncomeChildEligibilityBasis>
          <hix-core:StatusIndicator>false</hix-core:StatusIndicator>
          <hix-ee:EligibilityBasisStatusCode>Complete</hix-ee:EligibilityBasisStatusCode>
          <hix-ee:EligibilityBasisIneligibilityReasonText>127</hix-ee:EligibilityBasisIneligibilityReasonText>
          <hix-ee:EligibilityBasisDetermination>
            <nc:ActivityDate>
              <nc:DateTime>2024-07-25T13:10:39.345-05:00</nc:DateTime>
            </nc:ActivityDate>
          </hix-ee:EligibilityBasisDetermination>
        </hix-ee:CHIPTargetedLowIncomeChildEligibilityBasis>
        <hix-ee:CHIPUnbornChildCategoryEligibilityBasis>
          <hix-ee:EligibilityBasisStatusCode>NotApplicable</hix-ee:EligibilityBasisStatusCode>
          <hix-ee:EligibilityBasisIneligibilityReasonText>555</hix-ee:EligibilityBasisIneligibilityReasonText>
          <hix-ee:EligibilityBasisDetermination>
            <nc:ActivityDate>
              <nc:DateTime>2024-07-25T13:34:32.185-05:00</nc:DateTime>
            </nc:ActivityDate>
          </hix-ee:EligibilityBasisDetermination>
        </hix-ee:CHIPUnbornChildCategoryEligibilityBasis>
        <hix-ee:CHIPStateHealthBenefitsEligibilityBasis>
          <hix-ee:EligibilityBasisStatusCode>NotApplicable</hix-ee:EligibilityBasisStatusCode>
          <hix-ee:EligibilityBasisDetermination>
            <nc:ActivityDate>
              <nc:DateTime>2024-07-25T13:10:39.345-05:00</nc:DateTime>
            </nc:ActivityDate>
          </hix-ee:EligibilityBasisDetermination>
        </hix-ee:CHIPStateHealthBenefitsEligibilityBasis>
        <hix-ee:CHIPWaitingPeriodEligibilityBasis>
          <hix-ee:EligibilityBasisStatusCode>NotApplicable</hix-ee:EligibilityBasisStatusCode>
          <hix-ee:EligibilityBasisDetermination>
            <nc:ActivityDate>
              <nc:DateTime>2024-07-25T13:10:39.345-05:00</nc:DateTime>
            </nc:ActivityDate>
          </hix-ee:EligibilityBasisDetermination>
        </hix-ee:CHIPWaitingPeriodEligibilityBasis>
        <hix-ee:CHIPTraffickingVictimCategoryEligibilityBasis>
          <hix-ee:EligibilityBasisStatusCode>NotApplicable</hix-ee:EligibilityBasisStatusCode>
          <hix-ee:EligibilityBasisIneligibilityReasonText>569</hix-ee:EligibilityBasisIneligibilityReasonText>
          <hix-ee:EligibilityBasisDetermination>
            <nc:ActivityDate>
              <nc:DateTime>2024-07-25T13:10:39.345-05:00</nc:DateTime>
            </nc:ActivityDate>
          </hix-ee:EligibilityBasisDetermination>
        </hix-ee:CHIPTraffickingVictimCategoryEligibilityBasis>
        <hix-ee:CHIPTitleIIWorkQuartersMetEligibilityBasis>
          <hix-ee:EligibilityBasisStatusCode>NotApplicable</hix-ee:EligibilityBasisStatusCode>
          <hix-ee:EligibilityBasisIneligibilityReasonText>632</hix-ee:EligibilityBasisIneligibilityReasonText>
          <hix-ee:EligibilityBasisDetermination>
            <nc:ActivityDate>
              <nc:DateTime>2024-07-25T13:10:39.345-05:00</nc:DateTime>
            </nc:ActivityDate>
          </hix-ee:EligibilityBasisDetermination>
        </hix-ee:CHIPTitleIIWorkQuartersMetEligibilityBasis>
        <hix-ee:MedicaidHouseholdReference s:ref="mh2488215749215813586"/>
      </hix-ee:CHIPEligibility>
      <hix-ee:ExchangeEligibility s:id="e2488594365044915272">
        <hix-ee:EligibilityDetermination>
          <nc:ActivityDate>
            <nc:DateTime>2024-07-25T13:10:39.345-05:00</nc:DateTime>
          </nc:ActivityDate>
        </hix-ee:EligibilityDetermination>
        <hix-ee:EligibilityEstablishingSystem>
          <hix-core:InformationExchangeSystemCategoryCode>Exchange</hix-core:InformationExchangeSystemCategoryCode>
        </hix-ee:EligibilityEstablishingSystem>
        <hix-ee:ExchangeQHPResidencyEligibilityBasis>
          <hix-core:StatusIndicator>true</hix-core:StatusIndicator>
          <hix-ee:EligibilityBasisStatusCode>Complete</hix-ee:EligibilityBasisStatusCode>
          <hix-ee:EligibilityBasisDetermination>
            <nc:ActivityDate>
              <nc:DateTime>2024-07-25T13:14:05.441-05:00</nc:DateTime>
            </nc:ActivityDate>
          </hix-ee:EligibilityBasisDetermination>
          <hix-ee:MedicaidResidencyEligibilityBasisCorrectStateIndicator>true</hix-ee:MedicaidResidencyEligibilityBasisCorrectStateIndicator>
        </hix-ee:ExchangeQHPResidencyEligibilityBasis>
        <hix-ee:ExchangeVerifiedCitizenshipOrLawfulPresenceEligibilityBasis>
          <hix-core:StatusIndicator>true</hix-core:StatusIndicator>
          <hix-ee:EligibilityBasisStatusCode>Complete</hix-ee:EligibilityBasisStatusCode>
          <hix-ee:EligibilityBasisDetermination>
            <nc:ActivityDate>
              <nc:DateTime>2024-07-25T13:34:31.417-05:00</nc:DateTime>
            </nc:ActivityDate>
          </hix-ee:EligibilityBasisDetermination>
        </hix-ee:ExchangeVerifiedCitizenshipOrLawfulPresenceEligibilityBasis>
      </hix-ee:ExchangeEligibility>
      <hix-ee:ReferralActivity>
        <nc:ActivityIdentification>
          <nc:IdentificationID>FFM63662504036930611</nc:IdentificationID>
        </nc:ActivityIdentification>
        <nc:ActivityDate>
          <nc:DateTime>2024-07-25T13:34:36.501-05:00</nc:DateTime>
        </nc:ActivityDate>
        <hix-ee:ReferralActivitySenderReference s:ref="Sender"/>
        <hix-ee:ReferralActivityReceiverReference s:ref="medicaidReceiver"/>
        <hix-ee:ReferralActivityStatus>
          <hix-ee:ReferralActivityStatusCode>Initiated</hix-ee:ReferralActivityStatusCode>
          <hix-ee:ReferralActivityOverallVerificationStatusCode>Y</hix-ee:ReferralActivityOverallVerificationStatusCode>
        </hix-ee:ReferralActivityStatus>
        <hix-ee:ReferralActivityReasonCode>GapFilling</hix-ee:ReferralActivityReasonCode>
        <hix-ee:ReferralActivityEligibilityReasonReference s:ref="e2488594365044915267"/>
      </hix-ee:ReferralActivity>
    </hix-ee:InsuranceApplicant>
    <hix-ee:InsuranceApplicationRequestingFinancialAssistanceIndicator>true</hix-ee:InsuranceApplicationRequestingFinancialAssistanceIndicator>
    <hix-ee:InsuranceApplicationCoverageRenewalYearQuantity>2</hix-ee:InsuranceApplicationCoverageRenewalYearQuantity>
    <hix-ee:SSFSigner>
      <hix-core:RoleOfPersonReference s:ref="pe606552526913774413"/>
      <hix-ee:Signature>
        <hix-core:SignatureName>
          <nc:PersonFullName>Margo Kindred</nc:PersonFullName>
        </hix-core:SignatureName>
        <hix-core:SignatureDate>
          <nc:Date>2024-07-25</nc:Date>
        </hix-core:SignatureDate>
      </hix-ee:Signature>
      <hix-ee:SSFAttestation>
        <hix-ee:SSFAttestationCollectionsAgreementIndicator>false</hix-ee:SSFAttestationCollectionsAgreementIndicator>
        <hix-ee:SSFAttestationMedicaidObligationsIndicator>true</hix-ee:SSFAttestationMedicaidObligationsIndicator>
        <hix-ee:SSFAttestationNonPerjuryIndicator>true</hix-ee:SSFAttestationNonPerjuryIndicator>
        <hix-ee:SSFAttestationNotIncarceratedIndicator>true</hix-ee:SSFAttestationNotIncarceratedIndicator>
        <hix-ee:SSFAttestationInformationChangesIndicator>true</hix-ee:SSFAttestationInformationChangesIndicator>
      </hix-ee:SSFAttestation>
    </hix-ee:SSFSigner>
    <hix-ee:InsuranceApplicationRequestingMedicaidIndicator>false</hix-ee:InsuranceApplicationRequestingMedicaidIndicator>
    <hix-ee:SSFPrimaryContact>
      <hix-core:RoleOfPersonReference s:ref="pe606552526913774413"/>
      <hix-ee:SSFPrimaryContactPreferenceCode>Email</hix-ee:SSFPrimaryContactPreferenceCode>
    </hix-ee:SSFPrimaryContact>
    <hix-ee:InsuranceApplicationTaxReturnAccessIndicator>true</hix-ee:InsuranceApplicationTaxReturnAccessIndicator>
  </hix-ee:InsuranceApplication>
  <hix-ee:MedicaidHousehold s:id="mh2488215749215813585">
    <hix-ee:HouseholdIncome>
      <hix-core:IncomeFrequency>
        <hix-core:FrequencyCode>Annually</hix-core:FrequencyCode>
      </hix-core:IncomeFrequency>
      <hix-core:IncomeAmount>0.00</hix-core:IncomeAmount>
      <hix-core:IncomeCategoryCode>Unspecified</hix-core:IncomeCategoryCode>
    </hix-ee:HouseholdIncome>
    <hix-ee:HouseholdIncome>
      <hix-core:IncomeFrequency>
        <hix-core:FrequencyCode>Monthly</hix-core:FrequencyCode>
      </hix-core:IncomeFrequency>
      <hix-core:IncomeAmount>0.00</hix-core:IncomeAmount>
    </hix-ee:HouseholdIncome>
    <hix-ee:HouseholdMemberReference s:ref="pe606552526913774413"/>
    <hix-ee:HouseholdMemberReference s:ref="pe2488551408249964720"/>
    <hix-ee:MedicaidHouseholdEffectivePersonQuantity>2</hix-ee:MedicaidHouseholdEffectivePersonQuantity>
    <hix-ee:MedicaidHouseholdIncomeAboveHighestApplicableMAGIStandardIndicator>false</hix-ee:MedicaidHouseholdIncomeAboveHighestApplicableMAGIStandardIndicator>
  </hix-ee:MedicaidHousehold>
  <hix-ee:MedicaidHousehold s:id="mh2488215749215813586">
    <hix-ee:HouseholdIncome>
      <hix-core:IncomeFrequency>
        <hix-core:FrequencyCode>Annually</hix-core:FrequencyCode>
      </hix-core:IncomeFrequency>
      <hix-core:IncomeAmount>0.00</hix-core:IncomeAmount>
      <hix-core:IncomeCategoryCode>Unspecified</hix-core:IncomeCategoryCode>
    </hix-ee:HouseholdIncome>
    <hix-ee:HouseholdIncome>
      <hix-core:IncomeFrequency>
        <hix-core:FrequencyCode>Monthly</hix-core:FrequencyCode>
      </hix-core:IncomeFrequency>
      <hix-core:IncomeAmount>0.00</hix-core:IncomeAmount>
    </hix-ee:HouseholdIncome>
    <hix-ee:HouseholdMemberReference s:ref="pe606552526913774413"/>
    <hix-ee:HouseholdMemberReference s:ref="pe2488551408249964720"/>
    <hix-ee:MedicaidHouseholdEffectivePersonQuantity>2</hix-ee:MedicaidHouseholdEffectivePersonQuantity>
    <hix-ee:MedicaidHouseholdIncomeAboveHighestApplicableMAGIStandardIndicator>false</hix-ee:MedicaidHouseholdIncomeAboveHighestApplicableMAGIStandardIndicator>
  </hix-ee:MedicaidHousehold>
  <hix-core:Person s:id="pe606552526913774413">
    <nc:PersonAgeMeasure>
      <nc:MeasurePointValue>49</nc:MeasurePointValue>
    </nc:PersonAgeMeasure>
    <nc:PersonBirthDate>
      <nc:Date>DOB</nc:Date>
    </nc:PersonBirthDate>
    <nc:PersonLivingIndicator>true</nc:PersonLivingIndicator>
    <nc:PersonName>
      <nc:PersonGivenName>First name</nc:PersonGivenName>
      <nc:PersonSurName>Last</nc:PersonSurName>
    </nc:PersonName>
    <nc:PersonRaceText>White</nc:PersonRaceText>
    <nc:PersonSexText>Male</nc:PersonSexText>
    <nc:PersonSSNIdentification s:metadata="vm2488593601916468273">
      <nc:IdentificationID>SSN</nc:IdentificationID>
    </nc:PersonSSNIdentification>
    <nc:PersonUSCitizenIndicator s:metadata="vm2488593601916468274">true</nc:PersonUSCitizenIndicator>
    <hix-core:TribalAugmentation>
      <hix-core:PersonAmericanIndianOrAlaskaNativeIndicator>false</hix-core:PersonAmericanIndianOrAlaskaNativeIndicator>
    </hix-core:TribalAugmentation>
    <hix-core:PersonAugmentation>
      <hix-core:PersonAssociation>
        <nc:PersonReference s:ref="pe2488551408249964720"/>
        <hix-core:FamilyRelationshipCode>19</hix-core:FamilyRelationshipCode>
        <hix-core:PersonCaretakerDependentCode>No</hix-core:PersonCaretakerDependentCode>
      </hix-core:PersonAssociation>
      <hix-core:PersonContactInformationAssociation>
        <nc:ContactInformationIsPrimaryIndicator>true</nc:ContactInformationIsPrimaryIndicator>
        <hix-core:ContactInformation>
          <nc:ContactTelephoneNumber>
            <nc:FullTelephoneNumber>
              <nc:TelephoneNumberFullID>3189909458</nc:TelephoneNumberFullID>
            </nc:FullTelephoneNumber>
          </nc:ContactTelephoneNumber>
        </hix-core:ContactInformation>
        <hix-core:ContactInformationCategoryCode>Mobile</hix-core:ContactInformationCategoryCode>
      </hix-core:PersonContactInformationAssociation>
      <hix-core:PersonContactInformationAssociation>
        <nc:ContactInformationIsPrimaryIndicator>false</nc:ContactInformationIsPrimaryIndicator>
        <hix-core:ContactInformation>
          <nc:ContactMailingAddress>
            <nc:StructuredAddress>
              <nc:LocationStreet>
                <nc:StreetFullText>108 Miriam Lane</nc:StreetFullText>
              </nc:LocationStreet>
              <nc:LocationCityName>Shreport</nc:LocationCityName>
              <nc:LocationCountyName>CADDO</nc:LocationCountyName>
              <nc:LocationCountyCode>017</nc:LocationCountyCode>
              <nc:LocationStateUSPostalServiceCode>LA</nc:LocationStateUSPostalServiceCode>
              <nc:LocationPostalCode>71107</nc:LocationPostalCode>
            </nc:StructuredAddress>
          </nc:ContactMailingAddress>
        </hix-core:ContactInformation>
        <hix-core:ContactInformationCategoryCode>Home</hix-core:ContactInformationCategoryCode>
      </hix-core:PersonContactInformationAssociation>
      <hix-core:PersonContactInformationAssociation>
        <nc:ContactInformationIsPrimaryIndicator>false</nc:ContactInformationIsPrimaryIndicator>
        <hix-core:ContactInformation>
          <nc:ContactMailingAddress>
            <nc:StructuredAddress>
              <nc:LocationStreet>
                <nc:StreetFullText>107 Miriam Lane</nc:StreetFullText>
              </nc:LocationStreet>
              <nc:LocationCityName>Shreport</nc:LocationCityName>
              <nc:LocationCountyName>CADDO</nc:LocationCountyName>
              <nc:LocationCountyCode>017</nc:LocationCountyCode>
              <nc:LocationStateUSPostalServiceCode>LA</nc:LocationStateUSPostalServiceCode>
              <nc:LocationPostalCode>71106</nc:LocationPostalCode>
            </nc:StructuredAddress>
          </nc:ContactMailingAddress>
        </hix-core:ContactInformation>
        <hix-core:ContactInformationCategoryCode>Mailing</hix-core:ContactInformationCategoryCode>
      </hix-core:PersonContactInformationAssociation>
      <hix-core:PersonContactInformationAssociation>
        <nc:ContactInformationIsPrimaryIndicator>false</nc:ContactInformationIsPrimaryIndicator>
        <hix-core:ContactInformation>
          <nc:ContactMailingAddress>
            <nc:StructuredAddress>
              <nc:LocationStreet>
                <nc:StreetFullText>107 Miriam Lane</nc:StreetFullText>
              </nc:LocationStreet>
              <nc:LocationCityName>Shreport</nc:LocationCityName>
              <nc:LocationCountyName>CADDO</nc:LocationCountyName>
              <nc:LocationCountyCode>017</nc:LocationCountyCode>
              <nc:LocationStateUSPostalServiceCode>LA</nc:LocationStateUSPostalServiceCode>
              <nc:LocationPostalCode>71106</nc:LocationPostalCode>
            </nc:StructuredAddress>
          </nc:ContactMailingAddress>
        </hix-core:ContactInformation>
        <hix-core:ContactInformationCategoryCode>Residency</hix-core:ContactInformationCategoryCode>
      </hix-core:PersonContactInformationAssociation>
      <hix-core:PersonContactInformationAssociation>
        <nc:ContactInformationIsPrimaryIndicator>false</nc:ContactInformationIsPrimaryIndicator>
        <hix-core:ContactInformation>
          <nc:ContactEmailID>mrsmk7@gmail.com</nc:ContactEmailID>
        </hix-core:ContactInformation>
        <hix-core:ContactInformationCategoryCode>Home</hix-core:ContactInformationCategoryCode>
      </hix-core:PersonContactInformationAssociation>
      <hix-core:PersonEmploymentAssociation>
        <hix-core:Employer s:id="em2488221957440044444">
          <nc:OrganizationName>Wicker Place</nc:OrganizationName>
        </hix-core:Employer>
      </hix-core:PersonEmploymentAssociation>
      <hix-core:PersonPregnancyStatus>
        <hix-core:StatusIndicator>false</hix-core:StatusIndicator>
      </hix-core:PersonPregnancyStatus>
      <hix-core:PersonIncome>
        <hix-core:IncomeFrequency>
          <hix-core:FrequencyCode>Monthly</hix-core:FrequencyCode>
        </hix-core:IncomeFrequency>
        <hix-core:IncomeAmount>0.00</hix-core:IncomeAmount>
        <hix-core:IncomeCategoryCode>Wages</hix-core:IncomeCategoryCode>
        <hix-core:IncomeSourceOrganizationReference s:ref="em2488221957440044444"/>
      </hix-core:PersonIncome>
      <hix-core:PersonPreferredLanguage>
        <nc:LanguageName>English</nc:LanguageName>
        <nc:PersonSpeaksLanguageIndicator>true</nc:PersonSpeaksLanguageIndicator>
        <nc:PersonWritesLanguageIndicator>true</nc:PersonWritesLanguageIndicator>
      </hix-core:PersonPreferredLanguage>
      <hix-core:USNaturalizedCitizenIndicator>false</hix-core:USNaturalizedCitizenIndicator>
      <hix-core:PersonMarriedIndicator>true</hix-core:PersonMarriedIndicator>
    </hix-core:PersonAugmentation>
  </hix-core:Person>
  <hix-core:Person s:id="pe2488551408249964720">
    <nc:PersonAgeMeasure>
      <nc:MeasurePointValue>48</nc:MeasurePointValue>
    </nc:PersonAgeMeasure>
    <nc:PersonBirthDate>
      <nc:Date>dob2</nc:Date>
    </nc:PersonBirthDate>
    <nc:PersonLivingIndicator>true</nc:PersonLivingIndicator>
    <nc:PersonName>
      <nc:PersonGivenName>person2</nc:PersonGivenName>
      <nc:PersonSurName>person2 last</nc:PersonSurName>
    </nc:PersonName>
    <nc:PersonRaceText>White</nc:PersonRaceText>
    <nc:PersonSexText>Female</nc:PersonSexText>
    <nc:PersonSSNIdentification s:metadata="vm2488593601916468277">
      <nc:IdentificationID>SSN2</nc:IdentificationID>
    </nc:PersonSSNIdentification>
    <nc:PersonUSCitizenIndicator s:metadata="vm2488593601916468278">true</nc:PersonUSCitizenIndicator>
    <hix-core:TribalAugmentation>
      <hix-core:PersonAmericanIndianOrAlaskaNativeIndicator>false</hix-core:PersonAmericanIndianOrAlaskaNativeIndicator>
    </hix-core:TribalAugmentation>
    <hix-core:PersonAugmentation>
      <hix-core:PersonAssociation>
        <nc:PersonReference s:ref="pe606552526913774413"/>
        <hix-core:FamilyRelationshipCode>03</hix-core:FamilyRelationshipCode>
        <hix-core:PersonCaretakerDependentCode>No</hix-core:PersonCaretakerDependentCode>
      </hix-core:PersonAssociation>
      <hix-core:PersonContactInformationAssociation>
        <nc:ContactInformationIsPrimaryIndicator>false</nc:ContactInformationIsPrimaryIndicator>
        <hix-core:ContactInformation>
          <nc:ContactMailingAddress>
            <nc:StructuredAddress>
              <nc:LocationStreet>
                <nc:StreetFullText>108 Miriam Lane</nc:StreetFullText>
              </nc:LocationStreet>
              <nc:LocationCityName>Shreport</nc:LocationCityName>
              <nc:LocationCountyName>CADDO</nc:LocationCountyName>
              <nc:LocationCountyCode>017</nc:LocationCountyCode>
              <nc:LocationStateUSPostalServiceCode>LA</nc:LocationStateUSPostalServiceCode>
              <nc:LocationPostalCode>71107</nc:LocationPostalCode>
            </nc:StructuredAddress>
          </nc:ContactMailingAddress>
        </hix-core:ContactInformation>
        <hix-core:ContactInformationCategoryCode>Home</hix-core:ContactInformationCategoryCode>
      </hix-core:PersonContactInformationAssociation>
      <hix-core:PersonContactInformationAssociation>
        <nc:ContactInformationIsPrimaryIndicator>false</nc:ContactInformationIsPrimaryIndicator>
        <hix-core:ContactInformation>
          <nc:ContactMailingAddress>
            <nc:StructuredAddress>
              <nc:LocationStreet>
                <nc:StreetFullText>107 Miriam Lane</nc:StreetFullText>
              </nc:LocationStreet>
              <nc:LocationCityName>Shreport</nc:LocationCityName>
              <nc:LocationCountyName>CADDO</nc:LocationCountyName>
              <nc:LocationCountyCode>017</nc:LocationCountyCode>
              <nc:LocationStateUSPostalServiceCode>LA</nc:LocationStateUSPostalServiceCode>
              <nc:LocationPostalCode>71106</nc:LocationPostalCode>
            </nc:StructuredAddress>
          </nc:ContactMailingAddress>
        </hix-core:ContactInformation>
        <hix-core:ContactInformationCategoryCode>Residency</hix-core:ContactInformationCategoryCode>
      </hix-core:PersonContactInformationAssociation>
      <hix-core:PersonPregnancyStatus>
        <hix-core:StatusIndicator>false</hix-core:StatusIndicator>
      </hix-core:PersonPregnancyStatus>
      <hix-core:USNaturalizedCitizenIndicator>false</hix-core:USNaturalizedCitizenIndicator>
      <hix-core:PersonMarriedIndicator>true</hix-core:PersonMarriedIndicator>
    </hix-core:PersonAugmentation>
  </hix-core:Person>
  <hix-ee:TaxReturn>
    <hix-ee:TaxHousehold>
      <hix-ee:HouseholdIncome>
        <hix-core:IncomeAmount>0.00</hix-core:IncomeAmount>
        <hix-core:IncomeFederalPovertyLevelPercent>78</hix-core:IncomeFederalPovertyLevelPercent>
        <hix-core:IncomeVariableIndicator>true</hix-core:IncomeVariableIndicator>
      </hix-ee:HouseholdIncome>
      <hix-ee:HouseholdSizeQuantity>2</hix-ee:HouseholdSizeQuantity>
      <hix-ee:PrimaryTaxFiler>
        <hix-core:RoleOfPersonReference s:ref="pe606552526913774413"/>
      </hix-ee:PrimaryTaxFiler>
      <hix-ee:SpouseTaxFiler>
        <hix-core:RoleOfPersonReference s:ref="pe2488551408249964720"/>
      </hix-ee:SpouseTaxFiler>
    </hix-ee:TaxHousehold>
    <hix-ee:TaxReturnIncludesDependentIndicator>false</hix-ee:TaxReturnIncludesDependentIndicator>
  </hix-ee:TaxReturn>
  <hix-core:VerificationMetadata s:id="vm2488593601916468274">
    <hix-core:VerificationAuthorityTDS-FEPS-AlphaCode>SSA</hix-core:VerificationAuthorityTDS-FEPS-AlphaCode>
    <hix-core:VerificationDate>
      <nc:DateTime>2024-07-25T13:16:24.537-05:00</nc:DateTime>
    </hix-core:VerificationDate>
    <hix-core:VerificationRequestingSystem>
      <hix-core:InformationExchangeSystemCategoryCode>Exchange</hix-core:InformationExchangeSystemCategoryCode>
    </hix-core:VerificationRequestingSystem>
    <hix-core:VerificationIndicator>true</hix-core:VerificationIndicator>
    <hix-core:VerificationDescriptionText>Citizenship Status</hix-core:VerificationDescriptionText>
    <hix-core:VerificationStatus>
      <hix-core:VerificationStatusCode>5</hix-core:VerificationStatusCode>
    </hix-core:VerificationStatus>
    <hix-core:VerificationCategoryCode>Citizenship</hix-core:VerificationCategoryCode>
    <hix-core:ResponseCode>HS000000</hix-core:ResponseCode>
  </hix-core:VerificationMetadata>
  <hix-core:VerificationMetadata s:id="vm2488593601916468273">
    <hix-core:VerificationAuthorityTDS-FEPS-AlphaCode>SSA</hix-core:VerificationAuthorityTDS-FEPS-AlphaCode>
    <hix-core:VerificationDate>
      <nc:DateTime>2024-07-25T13:16:24.537-05:00</nc:DateTime>
    </hix-core:VerificationDate>
    <hix-core:VerificationRequestingSystem>
      <hix-core:InformationExchangeSystemCategoryCode>Exchange</hix-core:InformationExchangeSystemCategoryCode>
    </hix-core:VerificationRequestingSystem>
    <hix-core:VerificationIndicator>true</hix-core:VerificationIndicator>
    <hix-core:VerificationDescriptionText>SSN</hix-core:VerificationDescriptionText>
    <hix-core:VerificationStatus>
      <hix-core:VerificationStatusCode>5</hix-core:VerificationStatusCode>
    </hix-core:VerificationStatus>
    <hix-core:VerificationCategoryCode>SSN</hix-core:VerificationCategoryCode>
    <hix-core:ResponseCode>HS000000</hix-core:ResponseCode>
  </hix-core:VerificationMetadata>
  <hix-core:VerificationMetadata s:id="vm2488593601916468278">
    <hix-core:VerificationAuthorityTDS-FEPS-AlphaCode>SSA</hix-core:VerificationAuthorityTDS-FEPS-AlphaCode>
    <hix-core:VerificationDate>
      <nc:DateTime>2024-07-25T13:16:24.537-05:00</nc:DateTime>
    </hix-core:VerificationDate>
    <hix-core:VerificationRequestingSystem>
      <hix-core:InformationExchangeSystemCategoryCode>Exchange</hix-core:InformationExchangeSystemCategoryCode>
    </hix-core:VerificationRequestingSystem>
    <hix-core:VerificationIndicator>true</hix-core:VerificationIndicator>
    <hix-core:VerificationDescriptionText>Citizenship Status</hix-core:VerificationDescriptionText>
    <hix-core:VerificationStatus>
      <hix-core:VerificationStatusCode>5</hix-core:VerificationStatusCode>
    </hix-core:VerificationStatus>
    <hix-core:VerificationCategoryCode>Citizenship</hix-core:VerificationCategoryCode>
    <hix-core:ResponseCode>HS000000</hix-core:ResponseCode>
  </hix-core:VerificationMetadata>
  <hix-core:VerificationMetadata s:id="vm2488593601916468277">
    <hix-core:VerificationAuthorityTDS-FEPS-AlphaCode>SSA</hix-core:VerificationAuthorityTDS-FEPS-AlphaCode>
    <hix-core:VerificationDate>
      <nc:DateTime>2024-07-25T13:16:24.537-05:00</nc:DateTime>
    </hix-core:VerificationDate>
    <hix-core:VerificationRequestingSystem>
      <hix-core:InformationExchangeSystemCategoryCode>Exchange</hix-core:InformationExchangeSystemCategoryCode>
    </hix-core:VerificationRequestingSystem>
    <hix-core:VerificationIndicator>true</hix-core:VerificationIndicator>
    <hix-core:VerificationDescriptionText>SSN</hix-core:VerificationDescriptionText>
    <hix-core:VerificationStatus>
      <hix-core:VerificationStatusCode>5</hix-core:VerificationStatusCode>
    </hix-core:VerificationStatus>
    <hix-core:VerificationCategoryCode>SSN</hix-core:VerificationCategoryCode>
    <hix-core:ResponseCode>HS000000</hix-core:ResponseCode>
  </hix-core:VerificationMetadata>
  <ext:PhysicalHousehold>
    <hix-ee:HouseholdMemberReference s:ref="pe606552526913774413"/>
    <hix-ee:HouseholdMemberReference s:ref="pe2488551408249964720"/>
  </ext:PhysicalHousehold>
</exch:AccountTransferRequest>
 </soap:Body>
</soap:Envelope>